unique_id_generator/__init__.py
unique_id_generator/id_gen.py
unique_id_generator-0.1.0.dist-info/METADATA
unique_id_generator-0.1.0.dist-info/WHEEL
unique_id_generator-0.1.0.dist-info/top_level.txt
unique_id_generator-0.1.0.dist-info/RECORD
